{
    "fnapiio" : {
        "check" : "https://fortniteapi.io/v1/status"
    },
    "fnapicom" : {
        "check" : "https://fortnite-api.com/v2/aes",
        "accountid" : "https://fortnite-api.com/v2/stats/br/v2"
    },
    "github" : {
        "identity" : "https://raw.githubusercontent.com/Artlfmj/fn-progress-tracker/main/api/identity.json",
        "emergency-notices" : "https://raw.githubusercontent.com/Artlfmj/fn-progress-tracker/main/api/emergency.json",
        "releases" : "https://api.github.com/repos/artlfmj/fn-progress-tracker/releases"
    }
}